ifly_atp/__init__.py
ifly_atp/client.py
ifly_atp/config.py
ifly_atp/error.py
ifly_atp/pretrain/__init__.py
ifly_atp/pretrain/av2vec/__init__.py
ifly_atp/pretrain/av2vec/av2vec.py
ifly_atp/pretrain/av2vec/data.py
ifly_atp/pretrain/voice2vec/__init__.py
ifly_atp/pretrain/voice2vec/data.py
ifly_atp/pretrain/voice2vec/main.py
ifly_atp/pretrain/voice2vec/voice2vec.py
ifly_atp/utils/aipass_client.py
ifly_atp/utils/exception.py
ifly_atp/utils/log.py
ifly_atp/utils/ne_utils.py
ifly_atp-1.0.1.dist-info/WHEEL
ifly_atp-1.0.1.dist-info/METADATA
ifly_atp-1.0.1.dist-info/RECORD
