Metadata-Version: 2.1
Name: ifly-atp
Version: 1.0.1
Summary: an sdk for iflytek atp
Author: ybyang
Author-email: ybyang7@iflytek.com
Requires-Python: >=3.6
Classifier: Programming Language :: Python :: 3
Classifier: Programming Language :: Python :: 3.10
Classifier: Programming Language :: Python :: 3.6
Classifier: Programming Language :: Python :: 3.7
Classifier: Programming Language :: Python :: 3.8
Classifier: Programming Language :: Python :: 3.9
Requires-Dist: jsonpath_rw (>=1.4.0)
Requires-Dist: requests (>=2.26.0)
